{"name":"Nghi Gia Nghi Thất","folder":"nghigianghithat","tacGia":"Thời Câm","theLoai":"Ngôn Tình","trangThai":"Full","description":"Mười tám tuổi, Lục Dĩ Ngưng mới vào đại học, tóc ngắn xinh đẹp, mỉm cười rạng rỡ. Lúc đó, thiên kim Lục gia đã tùy ý bỏ qua tất cả các khóa học mình có thể chọn, một bước không rời theo sau Đường Mộ Bạch thi vào ngành Y nhàm chán vô vị.<br>Hai mươi lăm tuổi, Lục Dĩ Ngưng tốt nghiệp đại học danh tiếng hàng đầu, trong ngành nhiếp ảnh ở nước ngoài hô mưa gọi gió, quan hệ rộng rãi, lại chỉ duy nhất tránh không bao giờ nhắc đến Đường Mộ Bạch.<br>Trong vài năm, những tin đồn về Đường Mộ Bạch từ trong nước cũng truyền tới------- Tài hoa xuất chúng, hai mươi sáu tuổi đã ở giới y học nhất chiến thành danh.<br>Sau nhiều năm gặp lại, Lục Dĩ Ngưng thay bạn tốt Tâm Duyệt đến tìm bác phụ khoa tìm hiểu quân tình: \"Bác sĩ, tôi gần đây kinh nguyệt không đều, thích ăn chua, thích ngủ, còn hay nôn khan... có phải có rồi hay không?\"<br>Bác sĩ từ một xấp bệnh án dày cộp ngẩng đầu lên, lộ ra một gương mặt đẹp trai quen thuộc, ánh mắt âm trầm, thần sắc nguy hiểm: \"Có cái gì?\"<br>Lần đầu gặp lại, Lục Dĩ Ngưng thật bất hạnh mà ngã từ trên ghế xuống."}