{"name":"Lần Thứ Hai Tra Nam Sống Lại","folder":"lanthuhaitranamsonglai","tacGia":"Tiều Nguyệt Lâm Đồ","theLoai":"Ngôn Tình","trangThai":"Full","description":"Tác giả: Tiều Nguyệt Lâm Đồ<br><br>Chuyển ngữ: I.Majesty<br><br>Tag: Cổ đại, Cung đình hầu tước, HE, Sạch, Song xử, Cưng chiều, Trọng sinh, Xuyên không<br><br>Giới thiệu:<br><br>Chúc Hợp vốn là một người đàn ông bình thường của xã hội, một ngày nọ lại đột nhiên xuyên việt. Sau khi xuyên việt hắn nỗ lực mở ra con đường tiền đồ vô lượng của nam chính. Cũng như những nam chủ xuyên không khác, đầu tiên Chúc Hợp cưới một thê tử ôn nhu hiền thục xinh đẹp như hoa; sau đó cuộc sống xuất hiện đủ loại người đẹp, sinh được rất nhiều con cái.<br><br>Nhưng đến một ngày, con hắn chết hết.<br><br>Hắn đau đớn mà chất vấn thê tử hiền lương thục đức của hắn, vì sao nàng ta lại hại chết con hắn. Thê tử nói: “Tất cả đều là lỗi của ngươi”<br><br>Đời này sống lại, trong lòng Chúc Hợp vô cùng phấn khích, thê tử à lão công đến đây!<br><br>Nhưng Chúc Hợp phát hiện, tất cả vận may của bản thân hình như đều đã bị dùng hết vào kiếp trước rồi.<br>Ngựa đực văn, xuyên viêt thời không. Chuyện cũ về tra công sau khi trọng sinh hoàn toàn tỉnh ngộ, quyết định cải tà quy chính.<br>.....................................................................................................................................<br><br>Sau khi gả cho Chúc Hợp, Tạ Phác phát hiện luôn có nữ nhân vô tình hay cố ý muốn câu dẫn lão công nhà nàng, phải làm sao giờ?<br>Toàn bộ câu chuyện tràn ngập khí chất Vương Bá của nam chủ o(￣ヘ￣o#"}