{"name":"Tân Sinh","folder":"tansinh","tacGia":"Thần Vụ Quang","theLoai":"Ngôn Tình","trangThai":"Full","description":"Tác giả: Thần Vụ Quang<br><br>Chuyển ngữ: SAC<br><br>Tag: Cẩu huyết, Đô thị tình duyên, Gương vỡ lại lành, HE, Hiện đại, Ngọt, Cưng chiều<br><br>Giới thiệu:<br><br>Mười chín tuổi Quan Hiểu Ninh để bạn trai Nhan Dịch Trạch không bị phán tội nặng nên tự nguyện để bản thân đứng ra nhận lấy tội danh ngộ thương làm người ta tử vong.<br><br>Chỉ là cuộc sống sau khi cô ra tù đã có nhiều biến đổi mạnh. Nhan Dịch Trạch không chỉ không ngừng thăng quan tiến chức, rất nhanh đã nổi tiếng trong giới xã hội thượng lưu, lại còn có có vị hôn thê xinh đẹp ở bên cạnh..."}