{"name":"Lục Gia Tiểu Tức Phụ","folder":"lucgiatieutucphu","tacGia":"Tiếu Giai Nhân","theLoai":"Ngôn Tình","trangThai":"Đang ra","description":"Tác giả: Tiếu Giai Nhân<br><br>Thể loại: Ngôn Tình, Cổ Đại, Truyện Sủng, Điền Văn, Trọng Sinh<br><br>Giới thiệu:<br><br>Ngưng Hương đời trước là nha hoàn Hầu phủ. Bị thế tử phu nhân ghen ghét bán nàng và hảo tỷ muội Tố Nguyệt đi. Cùng đường phải nhảy xuống sông.&nbsp;<br><br>Sau khi trọng sinh, mục tiêu của nàng là chuộc thân, trở về chăm sóc đệ đệ thơ dại.<br><br>Trở về liền Lục Thành, nam nhân thôn bên cạnh để ý. Đã vậy hắn còn dùng \"nhi tử hai tuổi của mình làm cớ dây dưa.<br><br>Ngưng Hương gả qua, cuộc sống điền viên càng ngày càng tốt.<br><br>Bỗng một ngày, cha ruột của hài tử xuất hiện...<br><br>Tóm tắt ngắn gọn: cuộc sống của Ngưng Hương từ lúc là tiểu tức phụ nông gia đến nhạc mẫu thái tử..."}