{"name":"Anh Là Ngân Hà Khó Chạm Tới","folder":"anhlanganhakhochamtoi","tacGia":"Hồi Nam Tước","theLoai":"Ngôn Tình","trangThai":"Full","description":"Tác giả:&nbsp;Hồi Nam Tước<br><br>Thể loại:&nbsp;Ngôn tình, Hiện đại, HE, Tình cảm, Ngọt sủng, Ngược luyến, Nhẹ nhàng, Ấm áp, Đơn phương yêu thầm<br><br>Văn án:<br><br>Trong nhân sinh u ám của Cố Chiếu, nếu nói ông nội cô là ánh trời, bà nội cô là ánh trăng sáng thì Thẩm Quyết Tinh chính là ánh sao Bắc cực vĩnh viễn không bao giờ tắt.<br><br>Dẫu cho ánh sao ấy không ấm áp như ánh mặt trời, cũng không tỏa sáng rực rỡ như ánh trăng nhưng chính nó đã thắp sáng bầu trời đêm cằn cỗi của cô. Lúc cô mất mát, lúc cô cảm thấy mỏi mệt, lúc cuộc đời cô bị mây đen che khuất, ánh sao ấy đã mang đến cho cô một chút an ủi.<br><br>Cố Chiếu cũng không che giấu việc mình thích Thẩm Quyết Tinh, nhưng cô cũng không hy vọng xa vời người ấy sẽ thích lại mình.<br><br>Không phải cứ thích là sẽ được hồi đáp, đây chính là ánh sáng thanh xuân của cô, cô không muốn mang đến cho anh bất cứ phiền não hay gánh nặng nào cả.<br><br>***<br><br>Yêu đơn phương là lao đến trong vô vọng, em đứng ở đầu bên này, còn anh đứng ở bên kia dãy ngân hà.<br><br>Cô gái nhỏ tự ti đáng thương X Soái ca ngoài lạnh trong nóng"}